{"stat.useItem.minecraft.bow":1216,"stat.useItem.minecraft.quartz_block":341,"stat.leaveGame":47,"stat.killEntity.Parrot":1,"stat.pickup.minecraft.jungle_fence":49,"stat.drop.mw.sulfurdust":3,"stat.useItem.minecraft.glowstone":158,"stat.mineBlock.minecraft.sandstone":63,"stat.killEntity.PigZombie":12,"stat.mineBlock.minecraft.stained_glass":18,"stat.craftItem.minecraft.shield":3,"stat.mineBlock.minecraft.web":119,"stat.mineBlock.minecraft.red_sandstone":47,"stat.pickup.minecraft.leaves2":41,"stat.drop.minecraft.iron_sword":2,"stat.pickup.minecraft.rotten_flesh":915,"stat.pickup.minecraft.cobblestone_wall":2,"stat.pickup.minecraft.bucket":2,"stat.pickup.mw.leadore":48,"stat.useItem.minecraft.rail":1013,"stat.killEntity.Enderman":4,"stat.pickup.minecraft.leather_boots":15,"stat.craftItem.minecraft.iron_shovel":6,"stat.killEntity.Witch":3,"stat.useItem.minecraft.iron_pickaxe":1757,"stat.pickup.minecraft.stained_hardened_clay":83,"stat.useItem.minecraft.iron_shovel":3048,"stat.craftItem.minecraft.glass_pane":64,"stat.mineBlock.mw.copperore":265,"stat.mineBlock.minecraft.vine":38,"stat.pickup.minecraft.light_weighted_pressure_plate":4,"stat.pickup.minecraft.record_far":1,"stat.pickup.minecraft.wooden_shovel":1,"stat.furnaceInteraction":171,"stat.useItem.minecraft.nether_wart":3,"stat.mineBlock.minecraft.rail":401,"stat.killEntity.ZombieVillager":15,"stat.pickup.minecraft.nether_brick":152,"stat.pickup.minecraft.beef":48,"stat.craftItem.minecraft.golden_leggings":1,"stat.pickup.minecraft.leather_helmet":8,"stat.mineBlock.minecraft.stained_hardened_clay":83,"stat.mineBlock.mw.tantalumore":65,"stat.useItem.minecraft.acacia_fence":12,"stat.pickup.minecraft.potion":5,"stat.useItem.minecraft.flint_and_steel":255,"stat.mineBlock.minecraft.fence":1,"stat.useItem.minecraft.wheat_seeds":321,"stat.killEntity.Husk":26,"stat.pickup.mw.tantalumingot":64,"stat.pickup.minecraft.lever":1,"stat.deaths":9,"stat.pickup.minecraft.egg":36,"stat.mineBlock.minecraft.stone_pressure_plate":4,"stat.craftItem.minecraft.iron_pickaxe":6,"stat.drop.minecraft.torch":3,"stat.drop.minecraft.glass_bottle":2,"stat.pickup.mw.tantalumore":71,"stat.mineBlock.minecraft.light_weighted_pressure_plate":2,"stat.mineBlock.minecraft.tallgrass":315,"stat.fishCaught":65,"stat.pickup.minecraft.cooked_mutton":12,"stat.chestOpened":3920,"stat.craftItem.minecraft.light_weighted_pressure_plate":7,"stat.useItem.minecraft.stone":304,"stat.useItem.minecraft.jungle_fence":71,"stat.pickup.minecraft.arrow":395,"stat.pickup.minecraft.iron_sword":8,"stat.pickup.minecraft.wooden_pressure_plate":1,"stat.craftItem.minecraft.quartz_block":184,"stat.pickup.minecraft.gold_nugget":5,"stat.craftItem.minecraft.coal":252,"stat.pickup.minecraft.carrot":151,"stat.crouchOneCm":16023,"stat.mineBlock.minecraft.chest":11,"stat.pickup.minecraft.rail":495,"stat.craftItem.minecraft.diamond":27,"stat.craftItem.minecraft.iron_ingot":288,"stat.pickup.minecraft.painting":7,"stat.craftingTableInteraction":365,"stat.pickup.minecraft.nether_brick_fence":13,"stat.mineBlock.minecraft.log2":52,"stat.useItem.minecraft.reeds":20,"stat.pickup.minecraft.dye":147,"stat.mineBlock.minecraft.jungle_fence":1,"stat.pickup.minecraft.planks":69,"stat.pickup.backpacks16840.backpack":1,"stat.craftItem.minecraft.diamond_shovel":1,"stat.pickup.minecraft.wheat_seeds":771,"stat.mineBlock.minecraft.glass":268,"stat.mineBlock.minecraft.dirt":2517,"stat.pickup.minecraft.poisonous_potato":2,"stat.useItem.minecraft.bread":1,"stat.drop.minecraft.rotten_flesh":5,"stat.useItem.minecraft.cobblestone":2101,"stat.pickup.minecraft.magma":25,"stat.useItem.minecraft.gravel":1,"stat.mineBlock.minecraft.double_plant":15,"stat.minecartOneCm":2511702,"stat.craftItem.backpacks16840.backpack":2,"stat.pickup.minecraft.iron_pickaxe":2,"stat.craftItem.minecraft.gold_ingot":54,"stat.pickup.minecraft.chicken":3,"stat.pickup.minecraft.tipped_arrow":1,"stat.pickup.backpacks16840.quantum_backpack":1,"stat.pickup.mw.tactical_helmet":2,"stat.useItem.minecraft.glass_pane":53,"stat.pickup.minecraft.coal_block":64,"stat.craftItem.minecraft.bucket":12,"stat.useItem.minecraft.iron_sword":2399,"stat.craftItem.minecraft.planks":448,"stat.itemEnchanted":16,"stat.pickup.minecraft.stone_sword":2,"stat.craftItem.minecraft.fishing_rod":1,"stat.pickup.minecraft.book":7,"stat.useItem.minecraft.stonebrick":223,"stat.mineBlock.minecraft.log":88,"stat.craftItem.minecraft.wooden_door":3,"stat.useItem.minecraft.wooden_door":12,"stat.pickup.minecraft.iron_door":5,"stat.craftItem.minecraft.paper":63,"stat.pickup.minecraft.red_flower":2,"stat.pickup.minecraft.red_nether_brick":196,"stat.pickup.minecraft.wool":398,"stat.pickup.minecraft.cooked_fish":51,"stat.useItem.minecraft.wooden_axe":32,"stat.pickup.minecraft.red_sandstone_stairs":27,"stat.cakeSlicesEaten":7,"stat.useItem.minecraft.iron_axe":156,"stat.mineBlock.minecraft.cobblestone":842,"stat.pickup.minecraft.stone_pickaxe":11,"stat.pickup.minecraft.flint":24,"stat.mineBlock.minecraft.yellow_flower":5,"stat.pickup.minecraft.leather_chestplate":11,"stat.craftItem.minecraft.wool":49,"stat.pickup.mw.sulfurdust":264,"stat.pickup.minecraft.enchanted_book":18,"stat.pickup.minecraft.glowstone":56,"stat.pickup.minecraft.cooked_porkchop":12,"stat.pickup.mw.bauxiteore":38,"stat.useItem.minecraft.obsidian":64,"stat.useItem.minecraft.cookie":40,"stat.useItem.minecraft.stone_slab2":398,"stat.pickup.minecraft.bow":30,"stat.pickup.minecraft.iron_boots":10,"stat.pickup.minecraft.stone_hoe":1,"stat.craftItem.minecraft.furnace":36,"stat.craftItem.minecraft.lapis_block":7,"stat.pickup.mw.siliconore":20,"stat.useItem.minecraft.egg":2,"stat.craftItem.minecraft.iron_boots":2,"stat.pickup.minecraft.nether_wart_block":3,"stat.craftItem.mw.cloth":231,"stat.mineBlock.minecraft.obsidian":159,"stat.pickup.minecraft.shears":1,"stat.pickup.backpacks16840.quantum_chest":3,"stat.craftItem.minecraft.bow":2,"stat.pickup.minecraft.diamond_leggings":1,"stat.flyOneCm":661638,"stat.pickup.minecraft.sandstone":82,"stat.pickup.minecraft.nether_brick_stairs":17,"stat.pickup.minecraft.fish":65,"stat.useItem.backpacks16840.backpack":35,"stat.mineBlock.mw.tinore":27,"stat.timeSinceDeath":268012,"stat.useItem.minecraft.iron_door":2,"stat.craftItem.minecraft.iron_block":44,"stat.killEntity.Bat":1,"stat.craftItem.minecraft.stonebrick":5074,"stat.useItem.minecraft.potato":91,"stat.pickup.mw.tiningot":1,"stat.pickup.minecraft.chainmail_helmet":13,"stat.pickup.minecraft.nether_wart":40,"stat.mineBlock.minecraft.coal_ore":372,"stat.pickup.minecraft.shield":35,"stat.killEntity.Creeper":58,"stat.talkedToVillager":2,"stat.drop.minecraft.baked_potato":1,"stat.pickup.minecraft.wooden_sword":3,"stat.pickup.minecraft.string":912,"stat.craftItem.mw.greencloth":176,"stat.useItem.minecraft.milk_bucket":4,"stat.entityKilledBy.Skeleton":2,"stat.useItem.minecraft.written_book":1,"stat.sprintOneCm":6986119,"stat.useItem.minecraft.diamond_shovel":4172,"stat.mineBlock.minecraft.stone_slab":72,"stat.useItem.minecraft.hay_block":2,"stat.craftItem.minecraft.wooden_axe":1,"stat.mineBlock.minecraft.diamond_ore":2,"stat.pickup.minecraft.leather_leggings":12,"stat.craftItem.minecraft.wooden_pressure_plate":1,"stat.pickup.minecraft.sugar":3,"stat.killEntity.Zombie":328,"stat.mineBlock.minecraft.gold_ore":28,"stat.diveOneCm":160985,"stat.drop.minecraft.diamond_pickaxe":2,"stat.pickup.minecraft.wheat":318,"stat.mineBlock.minecraft.mossy_cobblestone":13,"stat.pickup.minecraft.sign":2,"stat.mineBlock.minecraft.stone_button":1,"stat.pickup.minecraft.stone_axe":1,"stat.pickup.minecraft.obsidian":222,"stat.useItem.minecraft.rotten_flesh":34,"stat.jump":14529,"stat.useItem.minecraft.sand":40,"stat.pickup.minecraft.coal":668,"stat.pickup.minecraft.iron_ingot":7,"stat.pickup.minecraft.gunpowder":74,"stat.craftItem.minecraft.torch":432,"stat.pickup.minecraft.dirt":2489,"stat.useItem.minecraft.light_weighted_pressure_plate":3,"stat.useItem.minecraft.glass":4540,"stat.pickup.minecraft.stone_shovel":2,"stat.useItem.minecraft.sapling":16,"stat.pickup.minecraft.gold_ore":33,"stat.mineBlock.minecraft.lapis_ore":18,"stat.pickup.minecraft.red_sandstone":45,"stat.pickup.minecraft.iron_axe":3,"stat.pickup.mw.marine_boots":1,"stat.mineBlock.minecraft.glass_pane":33,"stat.brewingstandInteraction":7,"stat.damageTaken":17339,"stat.mineBlock.minecraft.torch":190,"stat.mineBlock.minecraft.red_flower":1,"stat.pickup.minecraft.magma_cream":1,"stat.pickup.minecraft.log2":61,"stat.mineBlock.minecraft.sandstone_stairs":4,"stat.craftItem.minecraft.glowstone":205,"stat.pickup.minecraft.bed":45,"stat.pickup.minecraft.acacia_fence":16,"stat.pickup.minecraft.quartz_block":394,"stat.pickup.minecraft.potato":196,"stat.pickup.minecraft.rabbit_hide":1,"stat.entityKilledBy.Zombie":2,"stat.killEntity.Silverfish":32,"stat.craftItem.minecraft.stone_slab":507,"stat.animalsBred":60,"stat.useItem.minecraft.chest":4,"stat.pickup.minecraft.diamond_pickaxe":4,"stat.useItem.minecraft.tnt":1,"stat.useItem.minecraft.lava_bucket":14,"stat.craftItem.minecraft.spectral_arrow":2,"stat.craftItem.minecraft.iron_chestplate":2,"stat.pickup.minecraft.baked_potato":62,"stat.pickup.mw.makarovpm":4,"stat.useItem.minecraft.stained_hardened_clay":2,"stat.pickup.minecraft.ender_pearl":2,"stat.useItem.minecraft.redstone_ore":60,"stat.pickup.minecraft.ladder":2,"stat.pickup.minecraft.cooked_beef":11,"stat.useItem.minecraft.netherrack":7,"stat.killEntity.Stray":1,"stat.mineBlock.minecraft.tnt":7,"stat.mineBlock.minecraft.stonebrick":253,"stat.drop.minecraft.cookie":1,"stat.drop.minecraft.jungle_fence_gate":1,"stat.mineBlock.minecraft.glowstone":104,"stat.mobKills":1427,"stat.pickup.minecraft.diamond_boots":1,"stat.mineBlock.minecraft.bookshelf":1,"stat.craftItem.minecraft.shears":3,"stat.useItem.minecraft.mossy_cobblestone":11,"stat.pickup.minecraft.diamond":8,"stat.pickup.minecraft.iron_horse_armor":1,"stat.pickup.minecraft.beetroot_seeds":26,"stat.pickup.minecraft.torch":769,"stat.entityKilledBy.Silverfish":1,"stat.craftItem.backpacks16840.backpack_pouch":5,"stat.pickup.minecraft.record_stal":4,"stat.killEntity.Blaze":19,"stat.useItem.minecraft.mutton":1,"stat.pickup.minecraft.fishing_rod":2,"stat.useItem.minecraft.planks":32,"stat.pickup.minecraft.golden_boots":8,"stat.useItem.minecraft.golden_shovel":33,"stat.pickup.minecraft.glowstone_dust":308,"stat.pickup.minecraft.porkchop":6,"stat.pickup.minecraft.glass":466,"stat.useItem.minecraft.water_bucket":106,"stat.mineBlock.minecraft.stone_brick_stairs":24,"stat.mineBlock.minecraft.nether_brick_fence":10,"stat.pickup.minecraft.sand":4615,"stat.useItem.minecraft.red_nether_brick":105,"stat.pickup.minecraft.name_tag":1,"stat.pickup.minecraft.activator_rail":5,"stat.pickup.minecraft.chainmail_chestplate":5,"stat.mineBlock.minecraft.sand":4868,"stat.hopperInspected":94,"stat.pickup.minecraft.ghast_tear":1,"stat.pickup.minecraft.armor_stand":4,"stat.trappedChestTriggered":8,"stat.pickup.minecraft.furnace":1,"stat.mineBlock.minecraft.end_bricks":17,"stat.pickup.minecraft.iron_chestplate":10,"stat.pickup.minecraft.skull":1,"stat.pickup.minecraft.acacia_door":5,"stat.craftItem.mw.spetznaz_boots":13,"stat.killEntity.Horse":11,"stat.pickup.minecraft.stone_stairs":14,"stat.pickup.minecraft.golden_carrot":1,"stat.pickup.minecraft.saddle":1,"stat.mineBlock.minecraft.soul_sand":23,"stat.mineBlock.minecraft.oak_stairs":1,"stat.playOneMinute":3745136,"stat.pickup.minecraft.blaze_rod":22,"stat.craftItem.minecraft.diamond_block":4,"stat.useItem.minecraft.shears":4,"stat.pickup.minecraft.iron_bars":64,"stat.mineBlock.backpacks16840.quantum_chest":2,"stat.pickup.minecraft.netherrack":83,"stat.recordPlayed":3,"stat.craftItem.minecraft.carpet":96,"stat.mineBlock.minecraft.netherrack":80,"stat.pickup.minecraft.waterlily":1,"stat.pickup.minecraft.detector_rail":2,"stat.craftItem.minecraft.golden_rail":96,"stat.mineBlock.minecraft.gold_block":3,"stat.pickup.minecraft.cooked_chicken":8,"stat.fallOneCm":191464,"stat.craftItem.minecraft.chest":2,"stat.mineBlock.minecraft.lever":1,"stat.pickup.minecraft.red_mushroom":2,"stat.pickup.minecraft.golden_leggings":4,"stat.mineBlock.minecraft.nether_wart_block":4,"stat.useItem.minecraft.golden_rail":60,"stat.pickup.minecraft.feather":11,"stat.mineBlock.minecraft.red_nether_brick":241,"stat.pickup.mw.titaniumore":26,"stat.pickup.minecraft.iron_leggings":7,"stat.pickup.minecraft.lead":2,"stat.mineBlock.minecraft.gravel":145,"stat.useItem.minecraft.stone_pickaxe":2242,"stat.craftItem.minecraft.iron_leggings":8,"stat.useItem.minecraft.stone_sword":4,"stat.useItem.backpacks16840.quantum_backpack":16,"stat.useItem.minecraft.wool":69,"stat.pickup.minecraft.chainmail_boots":7,"stat.drop.minecraft.iron_axe":2,"stat.mineBlock.minecraft.quartz_stairs":128,"stat.pickup.minecraft.flint_and_steel":1,"stat.useItem.minecraft.torch":1011,"stat.pickup.mw.copperore":272,"stat.pickup.minecraft.iron_nugget":3,"stat.craftItem.minecraft.redstone_block":21,"stat.pickup.minecraft.crafting_table":6,"stat.craftItem.minecraft.crafting_table":3,"stat.mineBlock.mw.siliconore":20,"stat.killEntity.LavaSlime":11,"stat.pickup.minecraft.redstone_block":8,"stat.pickup.minecraft.log":100,"stat.craftItem.minecraft.stone_button":1,"stat.mineBlock.minecraft.golden_rail":8,"stat.pickup.minecraft.tallgrass":3,"stat.pickup.minecraft.chainmail_leggings":8,"stat.pickup.minecraft.sapling":18,"stat.pickup.minecraft.wooden_door":23,"stat.drop.minecraft.bow":1,"stat.pickup.minecraft.beetroot":12,"stat.pickup.mw.tinore":27,"stat.pickup.minecraft.diamond_helmet":2,"stat.killEntity.WitherSkeleton":11,"stat.pickup.minecraft.golden_sword":2,"stat.useItem.minecraft.stone_hoe":32,"stat.useItem.minecraft.beetroot_seeds":13,"stat.pickup.mw.spetznaz_chest":5,"stat.sneakTime":9236,"stat.mineBlock.minecraft.cobblestone_wall":1,"stat.entityKilledBy.Blaze":1,"stat.useItem.minecraft.baked_potato":346,"stat.pickup.minecraft.stone_slab":93,"stat.pickup.minecraft.yellow_flower":7,"stat.pickup.minecraft.golden_rail":110,"stat.useItem.minecraft.fishing_rod":92,"stat.pickup.minecraft.chest":17,"stat.drop.minecraft.stone_pickaxe":3,"stat.craftItem.minecraft.diamond_chestplate":1,"stat.pickup.minecraft.bone":284,"stat.useItem.minecraft.mushroom_stew":1,"stat.pickup.minecraft.stone_pressure_plate":5,"stat.pickup.minecraft.redstone_torch":47,"stat.horseOneCm":857634,"stat.useItem.minecraft.log2":2,"stat.mineBlock.minecraft.acacia_fence":12,"stat.useItem.minecraft.diamond_sword":2058,"stat.swimOneCm":357201,"stat.pickup.mw.spetznaz_boots":6,"stat.climbOneCm":235546,"stat.mineBlock.mw.sulfurore":187,"stat.craftItem.minecraft.gold_block":7,"stat.craftItem.minecraft.golden_chestplate":1,"stat.craftItem.mw.spetznaz_helmet":12,"stat.enderchestOpened":16,"stat.useItem.minecraft.dirt":962,"stat.pickup.minecraft.golden_helmet":1,"stat.mineBlock.mw.bauxiteore":36,"stat.mineBlock.mw.titaniumore":26,"stat.pickup.minecraft.anvil":11,"stat.useItem.minecraft.golden_pickaxe":7,"stat.craftItem.minecraft.stone_pickaxe":20,"stat.mineBlock.minecraft.magma":18,"stat.pickup.minecraft.cobblestone":5185,"stat.pickup.backpacks16840.backpack_pouch":4,"stat.pickup.minecraft.quartz_stairs":129,"stat.mineBlock.minecraft.carpet":57,"stat.pickup.minecraft.gold_block":2,"stat.mineBlock.minecraft.redstone_block":8,"stat.useItem.minecraft.stone_shovel":78,"stat.craftItem.minecraft.glass_bottle":3,"stat.pickup.minecraft.soul_sand":22,"stat.pickup.minecraft.glass_bottle":4,"stat.useItem.minecraft.cooked_beef":42,"stat.pickup.minecraft.cactus":12,"stat.pickup.minecraft.golden_pickaxe":2,"stat.pickup.minecraft.redstone":339,"stat.mineBlock.minecraft.iron_ore":310,"stat.craftItem.minecraft.book":5,"stat.pickup.minecraft.mutton":44,"stat.pickup.minecraft.mossy_cobblestone":14,"stat.drop.minecraft.iron_bars":4,"stat.mineBlock.minecraft.coal_block":12,"stat.pickup.minecraft.stonebrick":396,"stat.useItem.minecraft.cooked_porkchop":1,"stat.pickup.minecraft.iron_shovel":4,"stat.pickup.minecraft.carpet":60,"stat.pickup.minecraft.diamond_shovel":2,"stat.mineBlock.minecraft.nether_brick":124,"stat.mineBlock.minecraft.red_sandstone_stairs":24,"stat.pickup.minecraft.sandstone_stairs":3,"stat.pickup.minecraft.paper":6,"stat.craftItem.minecraft.stick":404,"stat.useItem.minecraft.stone_slab":403,"stat.craftItem.minecraft.stone":760,"stat.craftItem.minecraft.armor_stand":1,"stat.pickup.minecraft.grass":1,"stat.mineBlock.minecraft.crafting_table":4,"stat.useItem.minecraft.stone_pressure_plate":1,"stat.useItem.minecraft.diamond_pickaxe":5617,"stat.mineBlock.minecraft.quartz_block":365,"stat.useItem.minecraft.carrot":35,"stat.pickup.minecraft.diamond_chestplate":2,"stat.useItem.minecraft.bucket":169,"stat.entityKilledBy.Creeper":2,"stat.mineBlock.minecraft.planks":25,"stat.drop":31,"stat.pickup.minecraft.stone_button":1,"stat.killEntity.Sheep":33,"stat.pickup.minecraft.slime_ball":21,"stat.pickup.minecraft.golden_chestplate":2,"stat.craftItem.minecraft.diamond_pickaxe":2,"stat.useItem.minecraft.quartz_stairs":6,"stat.pickup.minecraft.gravel":151,"stat.useItem.minecraft.glass_bottle":1,"stat.killEntity.Slime":5,"stat.mineBlock.minecraft.anvil":11,"stat.useItem.minecraft.carpet":110,"stat.useItem.minecraft.potion":13,"stat.pickup.minecraft.stone_brick_stairs":16,"stat.pickup.minecraft.diamond_sword":7,"stat.killEntity.SkeletonHorse":1,"stat.pickup.minecraft.fence":3,"stat.pickup.minecraft.iron_helmet":17,"stat.pickup.minecraft.spider_eye":930,"stat.craftItem.minecraft.iron_helmet":2,"stat.mineBlock.mw.leadore":47,"stat.killEntity.bandit1":2,"stat.craftItem.minecraft.rail":720,"stat.drop.minecraft.bed":1,"stat.useItem.minecraft.cooked_chicken":2,"stat.pickup.minecraft.iron_ore":387,"stat.boatOneCm":479453,"stat.mineBlock.minecraft.iron_bars":59,"stat.craftItem.minecraft.flint_and_steel":5,"stat.pickup.minecraft.leaves":311,"stat.mineBlock.minecraft.leaves2":45,"stat.mineBlock.minecraft.stone_stairs":9,"stat.pickup.minecraft.leather":53,"stat.pickup.minecraft.reeds":71,"stat.killEntity.CaveSpider":10,"stat.useItem.minecraft.magma":3,"stat.pickup.minecraft.oak_stairs":1,"stat.damageDealt":149394,"stat.sleepInBed":116,"stat.craftItem.minecraft.anvil":2,"stat.pickup.minecraft.end_bricks":10,"stat.mineBlock.minecraft.nether_brick_stairs":17,"stat.killEntity.Cow":29,"stat.pickup.minecraft.minecart":57,"stat.killEntity.Pig":5,"stat.craftItem.minecraft.iron_sword":2,"stat.craftItem.minecraft.stone_shovel":1,"stat.walkOneCm":16636233,"stat.playerKills":1,"stat.pickup.minecraft.stick":29,"stat.craftItem.mw.spetznaz_chest":13,"stat.pickup.minecraft.tnt":7,"stat.pickup.minecraft.stone":814,"stat.mineBlock.minecraft.wool":45,"stat.craftItem.minecraft.hay_block":3,"stat.craftItem.minecraft.redstone":54,"stat.pickup.minecraft.gold_ingot":1,"stat.killEntity.Skeleton":130,"stat.mineBlock.minecraft.cactus":1,"stat.killEntity.Chicken":6,"stat.mineBlock.minecraft.redstone_torch":7,"stat.killEntity.Spider":510,"stat.mineBlock.minecraft.quartz_ore":187,"stat.pickup.minecraft.quartz":184,"stat.craftItem.minecraft.jungle_fence":57,"stat.pickup.minecraft.golden_shovel":3,"stat.mineBlock.minecraft.leaves":430,"stat.mineBlock.minecraft.redstone_ore":37,"stat.pickup.minecraft.lava_bucket":3,"stat.craftItem.minecraft.coal_block":62,"stat.pickup.mw.spetznaz_helmet":6,"stat.mineBlock.minecraft.stone":4324,"stat.useItem.minecraft.sandstone":77}